setup.py
dsnd_probability_cris/Binomialdistribution.py
dsnd_probability_cris/Gaussiandistribution.py
dsnd_probability_cris/Generaldistribution.py
dsnd_probability_cris/__init__.py
dsnd_probability_cris.egg-info/PKG-INFO
dsnd_probability_cris.egg-info/SOURCES.txt
dsnd_probability_cris.egg-info/dependency_links.txt
dsnd_probability_cris.egg-info/not-zip-safe
dsnd_probability_cris.egg-info/top_level.txt