Metadata-Version: 1.0
Name: dsnd-probability-cris
Version: 0.1
Summary: Gaussian and Binomial distributions
Home-page: UNKNOWN
Author: Cristyan Gil
Author-email: UNKNOWN
License: UNKNOWN
Platform: UNKNOWN
